numprim/__init__.py
numprim-1.0.dist-info/LICENSE
numprim-1.0.dist-info/METADATA
numprim-1.0.dist-info/WHEEL
numprim-1.0.dist-info/top_level.txt
numprim-1.0.dist-info/RECORD
